rf100vl/__init__.py
rf100vl/dataset.py
rf100vl/roboflow100vl.py
rf100vl/util.py
rf100vl/assets/dataset_name_to_basename.json
rf100vl/assets/dataset_name_to_category.json
rf100vl-1.1.0.dist-info/licenses/LICENSE
rf100vl-1.1.0.dist-info/METADATA
rf100vl-1.1.0.dist-info/WHEEL
rf100vl-1.1.0.dist-info/top_level.txt
rf100vl-1.1.0.dist-info/RECORD
