Metadata-Version: 2.4
Name: rf100vl
Version: 1.1.0
Summary: RF100-VL Dataset Interface
Author: Roboflow, Inc.
Author-email: peter@roboflow.com
Keywords: machine-learning,deep-learning,computer-vision,ML,DL,CV,AI
Classifier: Programming Language :: Python :: 3
Classifier: License :: OSI Approved :: MIT License
Classifier: Operating System :: OS Independent
Requires-Python: >=3.9
License-File: LICENSE
Requires-Dist: roboflow
Dynamic: author
Dynamic: author-email
Dynamic: classifier
Dynamic: description
Dynamic: description-content-type
Dynamic: keywords
Dynamic: license-file
Dynamic: requires-dist
Dynamic: requires-python
Dynamic: summary
